{
  "date" : "Fri, 16 Jan, 2026 16:18:56 +0000",
  "doco" : "For each file: start is seconds after start activity occurred. Length = milliseconds activity took",
  "files" : [
    {
      "name" : "/fsh-generated/resources/ImplementationGuide-ans.fhir.fr.[code].json",
      "size" : 5999,
      "processes" : [
        {
          "activity" : "load",
          "start" : 30,
          "length" : 177
        },
        {
          "activity" : "checkR4R4B",
          "start" : 32,
          "length" : 20
        },
        {
          "activity" : "generateNarratives",
          "start" : 32,
          "length" : 95
        },
        {
          "activity" : "validate",
          "start" : 40,
          "length" : 1700
        },
        {
          "activity" : "scanForUsageStats",
          "start" : 42,
          "length" : 1
        },
        {
          "activity" : "translate",
          "start" : 42,
          "length" : 15
        },
        {
          "activity" : "generate1",
          "start" : 42,
          "length" : 83
        },
        {
          "activity" : "generate2",
          "start" : 44,
          "length" : 114
        },
        {
          "activity" : "generateValidationPack",
          "start" : 54,
          "length" : 4
        }
      ]
    },
    {
      "name" : "fsh-generated/resources/CodeSystem-competence-code-system.json",
      "size" : 6320,
      "processes" : [
        {
          "activity" : "loadResources",
          "start" : 30,
          "length" : 15
        },
        {
          "activity" : "load",
          "start" : 30,
          "length" : 20
        },
        {
          "activity" : "scan",
          "start" : 31,
          "length" : 1
        },
        {
          "activity" : "loadDepInfo",
          "start" : 31,
          "length" : 1
        },
        {
          "activity" : "checkR4R4B",
          "start" : 32,
          "length" : 3
        },
        {
          "activity" : "generateNarratives",
          "start" : 32,
          "length" : 33
        },
        {
          "activity" : "validate",
          "start" : 35,
          "length" : 2063
        },
        {
          "activity" : "checkConformanceResources",
          "start" : 42,
          "length" : 1
        },
        {
          "activity" : "validate",
          "start" : 42,
          "length" : 1
        },
        {
          "activity" : "translate",
          "start" : 42,
          "length" : 7
        },
        {
          "activity" : "generate1",
          "start" : 42,
          "length" : 40
        },
        {
          "activity" : "generate2",
          "start" : 45,
          "length" : 848
        },
        {
          "activity" : "generateValidationPack",
          "start" : 54,
          "length" : 2
        }
      ]
    },
    {
      "name" : "fsh-generated/resources/CodeSystem-type-carte-code-system.json",
      "size" : 1008,
      "processes" : [
        {
          "activity" : "loadResources",
          "start" : 30,
          "length" : 11
        },
        {
          "activity" : "load",
          "start" : 30,
          "length" : 13
        },
        {
          "activity" : "generateNarratives",
          "start" : 32,
          "length" : 23
        },
        {
          "activity" : "validate",
          "start" : 37,
          "length" : 11
        },
        {
          "activity" : "translate",
          "start" : 42,
          "length" : 6
        },
        {
          "activity" : "generate1",
          "start" : 42,
          "length" : 16
        },
        {
          "activity" : "generate2",
          "start" : 45,
          "length" : 48
        }
      ]
    },
    {
      "name" : "fsh-generated/resources/Patient-frpatient-exemple.json",
      "size" : 453,
      "processes" : [
        {
          "activity" : "loadResources",
          "start" : 30,
          "length" : 12
        },
        {
          "activity" : "generateNarratives",
          "start" : 32,
          "length" : 254
        },
        {
          "activity" : "validate",
          "start" : 42,
          "length" : 9
        },
        {
          "activity" : "translate",
          "start" : 42,
          "length" : 5
        },
        {
          "activity" : "generate1",
          "start" : 42,
          "length" : 10
        },
        {
          "activity" : "generate2",
          "start" : 45,
          "length" : 11
        }
      ]
    },
    {
      "name" : "fsh-generated/resources/StructureDefinition-EyeColor.json",
      "size" : 1311,
      "processes" : [
        {
          "activity" : "loadResources",
          "start" : 30,
          "length" : 15
        },
        {
          "activity" : "load",
          "start" : 30,
          "length" : 7
        },
        {
          "activity" : "generateSnapshots",
          "start" : 31,
          "length" : 14
        },
        {
          "activity" : "checkR4R4B",
          "start" : 32,
          "length" : 1
        },
        {
          "activity" : "generateNarratives",
          "start" : 32,
          "length" : 66
        },
        {
          "activity" : "validate",
          "start" : 37,
          "length" : 2250
        },
        {
          "activity" : "checkConformanceResources",
          "start" : 42,
          "length" : 1
        },
        {
          "activity" : "translate",
          "start" : 42,
          "length" : 1
        },
        {
          "activity" : "generate1",
          "start" : 42,
          "length" : 46
        },
        {
          "activity" : "generate2",
          "start" : 45,
          "length" : 458
        },
        {
          "activity" : "generate2",
          "start" : 49,
          "length" : 214
        },
        {
          "activity" : "generateValidationPack",
          "start" : 54,
          "length" : 3
        },
        {
          "activity" : "scanProfilesForR5",
          "start" : 58,
          "length" : 1
        },
        {
          "activity" : "scanExamplesForR5",
          "start" : 58,
          "length" : 1
        }
      ]
    },
    {
      "name" : "fsh-generated/resources/StructureDefinition-fr-patient.json",
      "size" : 2350,
      "processes" : [
        {
          "activity" : "loadResources",
          "start" : 30,
          "length" : 15
        },
        {
          "activity" : "load",
          "start" : 30,
          "length" : 6
        },
        {
          "activity" : "generateSnapshots",
          "start" : 31,
          "length" : 105
        },
        {
          "activity" : "load-configure",
          "start" : 31,
          "length" : 1
        },
        {
          "activity" : "generateNarratives",
          "start" : 32,
          "length" : 59
        },
        {
          "activity" : "validate",
          "start" : 40,
          "length" : 316
        },
        {
          "activity" : "scanForUsageStats",
          "start" : 42,
          "length" : 2
        },
        {
          "activity" : "validate",
          "start" : 42,
          "length" : 1
        },
        {
          "activity" : "translate",
          "start" : 42,
          "length" : 1
        },
        {
          "activity" : "generate1",
          "start" : 42,
          "length" : 168
        },
        {
          "activity" : "generate2",
          "start" : 46,
          "length" : 502
        },
        {
          "activity" : "generate2",
          "start" : 49,
          "length" : 491
        },
        {
          "activity" : "generateValidationPack",
          "start" : 54,
          "length" : 12
        }
      ]
    },
    {
      "name" : "fsh-generated/resources/ValueSet-EyeColorVS.json",
      "size" : 669,
      "processes" : [
        {
          "activity" : "loadResources",
          "start" : 30,
          "length" : 14
        },
        {
          "activity" : "load",
          "start" : 30,
          "length" : 15
        },
        {
          "activity" : "generateNarratives",
          "start" : 32,
          "length" : 2973
        },
        {
          "activity" : "validate",
          "start" : 37,
          "length" : 43
        },
        {
          "activity" : "translate",
          "start" : 42,
          "length" : 5
        },
        {
          "activity" : "generate1",
          "start" : 42,
          "length" : 10
        },
        {
          "activity" : "generate2",
          "start" : 46,
          "length" : 2219
        }
      ]
    },
    {
      "name" : "fsh-generated/resources/ValueSet-MeltingPotVS.json",
      "size" : 881,
      "processes" : [
        {
          "activity" : "loadResources",
          "start" : 30,
          "length" : 11
        },
        {
          "activity" : "load",
          "start" : 30,
          "length" : 12
        },
        {
          "activity" : "checkR4R4B",
          "start" : 32,
          "length" : 1
        },
        {
          "activity" : "generateNarratives",
          "start" : 35,
          "length" : 190
        },
        {
          "activity" : "validate",
          "start" : 37,
          "length" : 13
        },
        {
          "activity" : "validate",
          "start" : 42,
          "length" : 1
        },
        {
          "activity" : "translate",
          "start" : 42,
          "length" : 5
        },
        {
          "activity" : "generate1",
          "start" : 42,
          "length" : 12
        },
        {
          "activity" : "generate2",
          "start" : 49,
          "length" : 245
        },
        {
          "activity" : "generateValidationPack",
          "start" : 54,
          "length" : 1
        }
      ]
    },
    {
      "name" : "fsh-generated/resources/ValueSet-ModifiedAdministrativeGender.json",
      "size" : 646,
      "processes" : [
        {
          "activity" : "loadResources",
          "start" : 30,
          "length" : 13
        },
        {
          "activity" : "load",
          "start" : 30,
          "length" : 12
        },
        {
          "activity" : "checkR4R4B",
          "start" : 32,
          "length" : 1
        },
        {
          "activity" : "generateNarratives",
          "start" : 35,
          "length" : 20
        },
        {
          "activity" : "validate",
          "start" : 37,
          "length" : 13
        },
        {
          "activity" : "translate",
          "start" : 42,
          "length" : 5
        },
        {
          "activity" : "generate1",
          "start" : 42,
          "length" : 11
        },
        {
          "activity" : "generate2",
          "start" : 49,
          "length" : 53
        }
      ]
    },
    {
      "name" : "fsh-generated/resources/ValueSet-TypeCarteVS.json",
      "size" : 417,
      "processes" : [
        {
          "activity" : "loadResources",
          "start" : 30,
          "length" : 12
        },
        {
          "activity" : "load",
          "start" : 30,
          "length" : 4
        },
        {
          "activity" : "checkR4R4B",
          "start" : 32,
          "length" : 1
        },
        {
          "activity" : "generateNarratives",
          "start" : 35,
          "length" : 18
        },
        {
          "activity" : "validate",
          "start" : 37,
          "length" : 8
        },
        {
          "activity" : "validate",
          "start" : 42,
          "length" : 1
        },
        {
          "activity" : "translate",
          "start" : 42,
          "length" : 4
        },
        {
          "activity" : "generate1",
          "start" : 42,
          "length" : 12
        },
        {
          "activity" : "generate2",
          "start" : 49,
          "length" : 52
        },
        {
          "activity" : "generateValidationPack",
          "start" : 54,
          "length" : 1
        }
      ]
    },
    {
      "name" : "/fsh-generated/includes/fsh-link-references.md",
      "size" : 453,
      "processes" : [
        {
          "activity" : "validate",
          "start" : 42,
          "length" : 1
        },
        {
          "activity" : "generate2",
          "start" : 49,
          "length" : 1
        }
      ]
    },
    {
      "name" : "/fsh-generated/includes/menu.xml",
      "size" : 2316
    },
    {
      "name" : "/input/data/features.yml",
      "size" : 164
    },
    {
      "name" : "/input/pagecontent/st_flux1.md",
      "size" : 119
    },
    {
      "name" : "/input/pagecontent/st_flux2.md",
      "size" : 118,
      "processes" : [
        {
          "activity" : "validate",
          "start" : 42,
          "length" : 1
        },
        {
          "activity" : "generate2",
          "start" : 49,
          "length" : 1
        }
      ]
    },
    {
      "name" : "/input/pagecontent/specifications_techniques.md",
      "size" : 0
    },
    {
      "name" : "/input/pagecontent/tests.md",
      "size" : 1184
    },
    {
      "name" : "/input/pagecontent/sf1.md",
      "size" : 119,
      "processes" : [
        {
          "activity" : "validate",
          "start" : 42,
          "length" : 1
        }
      ]
    },
    {
      "name" : "/input/pagecontent/specifications_fonctionnelles.md",
      "size" : 0,
      "processes" : [
        {
          "activity" : "validate",
          "start" : 42,
          "length" : 1
        }
      ]
    },
    {
      "name" : "/input/pagecontent/securite.md",
      "size" : 900
    },
    {
      "name" : "/input/pagecontent/construction_des_flux.md",
      "size" : 205,
      "processes" : [
        {
          "activity" : "validate",
          "start" : 42,
          "length" : 1
        }
      ]
    },
    {
      "name" : "/input/pagecontent/downloads.md",
      "size" : 1727,
      "processes" : [
        {
          "activity" : "validate",
          "start" : 42,
          "length" : 2
        },
        {
          "activity" : "generate2",
          "start" : 49,
          "length" : 1
        }
      ]
    },
    {
      "name" : "/input/pagecontent/change-log.md",
      "size" : 330,
      "processes" : [
        {
          "activity" : "validate",
          "start" : 42,
          "length" : 1
        }
      ]
    },
    {
      "name" : "/input/pagecontent/index.md",
      "size" : 2186
    },
    {
      "name" : "/input/pagecontent/autres_ressources.md",
      "size" : 155,
      "processes" : [
        {
          "activity" : "validate",
          "start" : 42,
          "length" : 1
        }
      ]
    },
    {
      "name" : "/template/config",
      "size" : 0
    },
    {
      "name" : "/template/config/_config.yml",
      "size" : 140,
      "processes" : [
        {
          "activity" : "validate",
          "start" : 42,
          "length" : 1
        }
      ]
    },
    {
      "name" : "/input/images",
      "size" : 0
    },
    {
      "name" : "/input/images/anImage.png",
      "size" : 36288,
      "processes" : [
        {
          "activity" : "validate",
          "start" : 42,
          "length" : 1
        }
      ]
    },
    {
      "name" : "/input/images/ci-sis-logo.png",
      "size" : 61365,
      "processes" : [
        {
          "activity" : "generate2",
          "start" : 49,
          "length" : 1
        }
      ]
    },
    {
      "name" : "/temp/pages/_includes/artifacts.xml",
      "size" : 5610
    }
  ]
}
